myenv/__init__.py
myenv-201902.7.dist-info/LICENSE
myenv-201902.7.dist-info/METADATA
myenv-201902.7.dist-info/WHEEL
myenv-201902.7.dist-info/top_level.txt
myenv-201902.7.dist-info/zip-safe
myenv-201902.7.dist-info/RECORD
